[
  { "itemId": "asgari-ucret", "yil": 2005, "deger": 350.15, "tip": "net", "kaynakTipi": "elle", "kaynakAdi": "Aile ve Sosyal Hizmetler Bakanlığı", "kaynakURL": "https://www.aile.gov.tr/media/35787/yillar-itibariyle-net-brut-asgari-ucretler.pdf", "dogrulama": "dogrulanmis", "not": "01.01.2005-31.12.2005, 16 yaşını dolduranlar net aylık" },
  { "itemId": "asgari-ucret", "yil": 2006, "deger": 380.46, "tip": "net", "kaynakTipi": "elle", "kaynakAdi": "Aile ve Sosyal Hizmetler Bakanlığı", "kaynakURL": "https://www.aile.gov.tr/media/35787/yillar-itibariyle-net-brut-asgari-ucretler.pdf", "dogrulama": "dogrulanmis", "not": "01.01.2006-31.12.2006 net aylık" },
  { "itemId": "asgari-ucret", "yil": 2007, "deger": 403.03, "tip": "net", "kaynakTipi": "elle", "kaynakAdi": "Aile ve Sosyal Hizmetler Bakanlığı", "kaynakURL": "https://www.aile.gov.tr/media/35787/yillar-itibariyle-net-brut-asgari-ucretler.pdf", "dogrulama": "dogrulanmis", "not": "Ocak (ilk yarı) tutarı; ikinci yarı 419,15 TL" },
  { "itemId": "asgari-ucret", "yil": 2008, "deger": 481.55, "tip": "net", "kaynakTipi": "elle", "kaynakAdi": "Aile ve Sosyal Hizmetler Bakanlığı", "kaynakURL": "https://www.aile.gov.tr/media/35787/yillar-itibariyle-net-brut-asgari-ucretler.pdf", "dogrulama": "dogrulanmis", "not": "Ocak (ilk yarı) tutarı; ikinci yarı 503,26 TL" },
  { "itemId": "asgari-ucret", "yil": 2009, "deger": 527.13, "tip": "net", "kaynakTipi": "elle", "kaynakAdi": "Aile ve Sosyal Hizmetler Bakanlığı", "kaynakURL": "https://www.aile.gov.tr/media/35787/yillar-itibariyle-net-brut-asgari-ucretler.pdf", "dogrulama": "dogrulanmis", "not": "Ocak (ilk yarı) tutarı; ikinci yarı 546,48 TL" },
  { "itemId": "asgari-ucret", "yil": 2010, "deger": 576.57, "tip": "net", "kaynakTipi": "elle", "kaynakAdi": "Aile ve Sosyal Hizmetler Bakanlığı", "kaynakURL": "https://www.aile.gov.tr/media/35787/yillar-itibariyle-net-brut-asgari-ucretler.pdf", "dogrulama": "dogrulanmis", "not": "Ocak (ilk yarı) tutarı; ikinci yarı 599,12 TL" },
  { "itemId": "asgari-ucret", "yil": 2011, "deger": 629.96, "tip": "net", "kaynakTipi": "elle", "kaynakAdi": "Aile ve Sosyal Hizmetler Bakanlığı", "kaynakURL": "https://www.aile.gov.tr/media/35787/yillar-itibariyle-net-brut-asgari-ucretler.pdf", "dogrulama": "dogrulanmis", "not": "Ocak (ilk yarı) tutarı; ikinci yarı 658,95 TL" },
  { "itemId": "asgari-ucret", "yil": 2012, "deger": 701.13, "tip": "net", "kaynakTipi": "elle", "kaynakAdi": "Aile ve Sosyal Hizmetler Bakanlığı", "kaynakURL": "https://www.aile.gov.tr/media/35787/yillar-itibariyle-net-brut-asgari-ucretler.pdf", "dogrulama": "dogrulanmis", "not": "Ocak (ilk yarı) tutarı; ikinci yarı 739,79 TL" },
  { "itemId": "asgari-ucret", "yil": 2013, "deger": 773.01, "tip": "net", "kaynakTipi": "elle", "kaynakAdi": "Aile ve Sosyal Hizmetler Bakanlığı", "kaynakURL": "https://www.aile.gov.tr/media/35787/yillar-itibariyle-net-brut-asgari-ucretler.pdf", "dogrulama": "dogrulanmis", "not": "Ocak (ilk yarı) tutarı; ikinci yarı 803,68 TL" },
  { "itemId": "asgari-ucret", "yil": 2014, "deger": 846.00, "tip": "net", "kaynakTipi": "elle", "kaynakAdi": "Aile ve Sosyal Hizmetler Bakanlığı", "kaynakURL": "https://www.aile.gov.tr/media/35787/yillar-itibariyle-net-brut-asgari-ucretler.pdf", "dogrulama": "dogrulanmis", "not": "Ocak (ilk yarı) tutarı; ikinci yarı 891,03 TL" },
  { "itemId": "asgari-ucret", "yil": 2015, "deger": 949.07, "tip": "net", "kaynakTipi": "elle", "kaynakAdi": "Aile ve Sosyal Hizmetler Bakanlığı", "kaynakURL": "https://www.aile.gov.tr/media/35787/yillar-itibariyle-net-brut-asgari-ucretler.pdf", "dogrulama": "dogrulanmis", "not": "Ocak (ilk yarı) tutarı; ikinci yarı 1.000,54 TL" },
  { "itemId": "asgari-ucret", "yil": 2016, "deger": 1300.99, "tip": "net", "kaynakTipi": "elle", "kaynakAdi": "Aile ve Sosyal Hizmetler Bakanlığı", "kaynakURL": "https://www.aile.gov.tr/media/35787/yillar-itibariyle-net-brut-asgari-ucretler.pdf", "dogrulama": "dogrulanmis", "not": "01.01.2016-31.12.2016 net aylık" },
  { "itemId": "asgari-ucret", "yil": 2017, "deger": 1404.06, "tip": "net", "kaynakTipi": "elle", "kaynakAdi": "Aile ve Sosyal Hizmetler Bakanlığı", "kaynakURL": "https://www.aile.gov.tr/media/35787/yillar-itibariyle-net-brut-asgari-ucretler.pdf", "dogrulama": "dogrulanmis", "not": "01.01.2017-31.12.2017 net aylık" },
  { "itemId": "asgari-ucret", "yil": 2018, "deger": 1603.12, "tip": "net", "kaynakTipi": "elle", "kaynakAdi": "Aile ve Sosyal Hizmetler Bakanlığı", "kaynakURL": "https://www.aile.gov.tr/media/35787/yillar-itibariyle-net-brut-asgari-ucretler.pdf", "dogrulama": "dogrulanmis", "not": "01.01.2018-31.12.2018 net aylık" },
  { "itemId": "asgari-ucret", "yil": 2019, "deger": 2020.90, "tip": "net", "kaynakTipi": "elle", "kaynakAdi": "Aile ve Sosyal Hizmetler Bakanlığı", "kaynakURL": "https://www.aile.gov.tr/media/35787/yillar-itibariyle-net-brut-asgari-ucretler.pdf", "dogrulama": "dogrulanmis", "not": "01.01.2019-31.12.2019 net aylık" },
  { "itemId": "asgari-ucret", "yil": 2020, "deger": 2324.71, "tip": "net", "kaynakTipi": "elle", "kaynakAdi": "Aile ve Sosyal Hizmetler Bakanlığı", "kaynakURL": "https://www.aile.gov.tr/media/35787/yillar-itibariyle-net-brut-asgari-ucretler.pdf", "dogrulama": "dogrulanmis", "not": "01.01.2020-31.12.2020 net aylık" },
  { "itemId": "asgari-ucret", "yil": 2021, "deger": 2825.90, "tip": "net", "kaynakTipi": "elle", "kaynakAdi": "Aile ve Sosyal Hizmetler Bakanlığı", "kaynakURL": "https://www.aile.gov.tr/media/35787/yillar-itibariyle-net-brut-asgari-ucretler.pdf", "dogrulama": "dogrulanmis", "not": "01.01.2021-31.12.2021 net aylık" },
  { "itemId": "asgari-ucret", "yil": 2022, "deger": 4253.40, "tip": "net", "kaynakTipi": "elle", "kaynakAdi": "Çalışma ve Sosyal Güvenlik Bakanlığı", "kaynakURL": "https://www.csgb.gov.tr/poco-pages/asgari-ucret/", "dogrulama": "dogrulanmis", "not": "Ocak (ilk yarı) tutarı; 01.07.2022'den itibaren 5.500,35 TL" },
  { "itemId": "asgari-ucret", "yil": 2023, "deger": 8506.80, "tip": "net", "kaynakTipi": "elle", "kaynakAdi": "Çalışma ve Sosyal Güvenlik Bakanlığı", "kaynakURL": "https://www.csgb.gov.tr/poco-pages/asgari-ucret/", "dogrulama": "dogrulanmis", "not": "Ocak (ilk yarı) tutarı; 01.07.2023'ten itibaren 11.402,32 TL" },
  { "itemId": "asgari-ucret", "yil": 2024, "deger": 17002.12, "tip": "net", "kaynakTipi": "elle", "kaynakAdi": "Çalışma ve Sosyal Güvenlik Bakanlığı", "kaynakURL": "https://www.csgb.gov.tr/poco-pages/asgari-ucret/", "dogrulama": "dogrulanmis", "not": "01.01.2024-31.12.2024 net aylık" },
  { "itemId": "asgari-ucret", "yil": 2025, "deger": 22104.67, "tip": "net", "kaynakTipi": "elle", "kaynakAdi": "Çalışma ve Sosyal Güvenlik Bakanlığı", "kaynakURL": "https://www.csgb.gov.tr/poco-pages/asgari-ucret/", "dogrulama": "dogrulanmis", "not": "01.01.2025-31.12.2025 net aylık" },
  { "itemId": "asgari-ucret", "yil": 2026, "deger": 28075.50, "tip": "net", "kaynakTipi": "elle", "kaynakAdi": "Çalışma ve Sosyal Güvenlik Bakanlığı", "kaynakURL": "https://www.csgb.gov.tr/poco-pages/asgari-ucret/", "dogrulama": "dogrulanmis", "not": "01.01.2026-31.12.2026 yürürlükteki net aylık (Haziran 2026 itibarıyla)" }
]
