[
  { "itemId": "ekmek", "yil": 2005, "deger": 1.19, "tip": "ortalama", "kaynakTipi": "elle", "kaynakAdi": "TÜİK", "kaynakURL": "https://www.verikaynagi.com/grafik/yillara-gore-ekmegin-kilogram-fiyati/", "dogrulama": "dogrulanmis", "not": "TÜİK aylık ekmek (1 kg) fiyatlarından yıllık ortalama; verikaynagi.com derlemesi. USD×asgari ücret oranı ile makullük kontrolü yapıldı." },
  { "itemId": "ekmek", "yil": 2006, "deger": 1.31, "tip": "ortalama", "kaynakTipi": "elle", "kaynakAdi": "TÜİK", "kaynakURL": "https://www.verikaynagi.com/grafik/yillara-gore-ekmegin-kilogram-fiyati/", "dogrulama": "dogrulanmis", "not": "TÜİK yıllık ortalama (1 kg)" },
  { "itemId": "ekmek", "yil": 2007, "deger": 1.55, "tip": "ortalama", "kaynakTipi": "elle", "kaynakAdi": "TÜİK", "kaynakURL": "https://www.verikaynagi.com/grafik/yillara-gore-ekmegin-kilogram-fiyati/", "dogrulama": "dogrulanmis", "not": "TÜİK yıllık ortalama (1 kg)" },
  { "itemId": "ekmek", "yil": 2008, "deger": 2.02, "tip": "ortalama", "kaynakTipi": "elle", "kaynakAdi": "TÜİK", "kaynakURL": "https://www.verikaynagi.com/grafik/yillara-gore-ekmegin-kilogram-fiyati/", "dogrulama": "dogrulanmis", "not": "TÜİK yıllık ortalama (1 kg)" },
  { "itemId": "ekmek", "yil": 2009, "deger": 2.07, "tip": "ortalama", "kaynakTipi": "elle", "kaynakAdi": "TÜİK", "kaynakURL": "https://www.verikaynagi.com/grafik/yillara-gore-ekmegin-kilogram-fiyati/", "dogrulama": "dogrulanmis", "not": "TÜİK yıllık ortalama (1 kg)" },
  { "itemId": "ekmek", "yil": 2010, "deger": 2.06, "tip": "ortalama", "kaynakTipi": "elle", "kaynakAdi": "TÜİK", "kaynakURL": "https://www.verikaynagi.com/grafik/yillara-gore-ekmegin-kilogram-fiyati/", "dogrulama": "dogrulanmis", "not": "TÜİK yıllık ortalama (1 kg)" },
  { "itemId": "ekmek", "yil": 2011, "deger": 2.20, "tip": "ortalama", "kaynakTipi": "elle", "kaynakAdi": "TÜİK", "kaynakURL": "https://www.verikaynagi.com/grafik/yillara-gore-ekmegin-kilogram-fiyati/", "dogrulama": "dogrulanmis", "not": "TÜİK yıllık ortalama (1 kg)" },
  { "itemId": "ekmek", "yil": 2012, "deger": 2.46, "tip": "ortalama", "kaynakTipi": "elle", "kaynakAdi": "TÜİK", "kaynakURL": "https://www.verikaynagi.com/grafik/yillara-gore-ekmegin-kilogram-fiyati/", "dogrulama": "dogrulanmis", "not": "TÜİK yıllık ortalama (1 kg)" },
  { "itemId": "ekmek", "yil": 2013, "deger": 2.81, "tip": "ortalama", "kaynakTipi": "elle", "kaynakAdi": "TÜİK", "kaynakURL": "https://www.verikaynagi.com/grafik/yillara-gore-ekmegin-kilogram-fiyati/", "dogrulama": "dogrulanmis", "not": "TÜİK yıllık ortalama (1 kg)" },
  { "itemId": "ekmek", "yil": 2014, "deger": 3.20, "tip": "ortalama", "kaynakTipi": "elle", "kaynakAdi": "TÜİK", "kaynakURL": "https://www.verikaynagi.com/grafik/yillara-gore-ekmegin-kilogram-fiyati/", "dogrulama": "dogrulanmis", "not": "TÜİK yıllık ortalama (1 kg)" },
  { "itemId": "ekmek", "yil": 2015, "deger": 3.48, "tip": "ortalama", "kaynakTipi": "elle", "kaynakAdi": "TÜİK", "kaynakURL": "https://www.verikaynagi.com/grafik/yillara-gore-ekmegin-kilogram-fiyati/", "dogrulama": "dogrulanmis", "not": "TÜİK yıllık ortalama (1 kg)" },
  { "itemId": "ekmek", "yil": 2016, "deger": 3.83, "tip": "ortalama", "kaynakTipi": "elle", "kaynakAdi": "TÜİK", "kaynakURL": "https://www.verikaynagi.com/grafik/yillara-gore-ekmegin-kilogram-fiyati/", "dogrulama": "dogrulanmis", "not": "TÜİK yıllık ortalama (1 kg)" },
  { "itemId": "ekmek", "yil": 2017, "deger": 4.08, "tip": "ortalama", "kaynakTipi": "elle", "kaynakAdi": "TÜİK", "kaynakURL": "https://www.verikaynagi.com/grafik/yillara-gore-ekmegin-kilogram-fiyati/", "dogrulama": "dogrulanmis", "not": "TÜİK yıllık ortalama (1 kg)" },
  { "itemId": "ekmek", "yil": 2018, "deger": 4.63, "tip": "ortalama", "kaynakTipi": "elle", "kaynakAdi": "TÜİK", "kaynakURL": "https://www.verikaynagi.com/grafik/yillara-gore-ekmegin-kilogram-fiyati/", "dogrulama": "dogrulanmis", "not": "TÜİK yıllık ortalama (1 kg)" },
  { "itemId": "ekmek", "yil": 2019, "deger": 5.43, "tip": "ortalama", "kaynakTipi": "elle", "kaynakAdi": "TÜİK", "kaynakURL": "https://www.verikaynagi.com/grafik/yillara-gore-ekmegin-kilogram-fiyati/", "dogrulama": "dogrulanmis", "not": "TÜİK yıllık ortalama (1 kg)" },
  { "itemId": "ekmek", "yil": 2020, "deger": 6.40, "tip": "ortalama", "kaynakTipi": "elle", "kaynakAdi": "TÜİK", "kaynakURL": "https://www.verikaynagi.com/grafik/yillara-gore-ekmegin-kilogram-fiyati/", "dogrulama": "dogrulanmis", "not": "TÜİK yıllık ortalama (1 kg)" },
  { "itemId": "ekmek", "yil": 2021, "deger": 8.07, "tip": "ortalama", "kaynakTipi": "elle", "kaynakAdi": "TÜİK", "kaynakURL": "https://www.verikaynagi.com/grafik/yillara-gore-ekmegin-kilogram-fiyati/", "dogrulama": "dogrulanmis", "not": "TÜİK yıllık ortalama (1 kg); seri Ocak 2022'de bitiyor, 2022-2026 ayrıca eklenecek" },

  { "itemId": "tavuk", "yil": 2005, "deger": 3.13, "tip": "ortalama", "kaynakTipi": "elle", "kaynakAdi": "TÜİK", "kaynakURL": "https://www.verikaynagi.com/grafik/yillara-gore-ortalama-tavuk-eti-fiyati-2009-2019/", "dogrulama": "dogrulanmis", "not": "TÜİK aylık tavuk eti (1 kg) fiyatlarından yıllık ortalama; verikaynagi (Playwright/XHR)" },
  { "itemId": "tavuk", "yil": 2006, "deger": 3.33, "tip": "ortalama", "kaynakTipi": "elle", "kaynakAdi": "TÜİK", "kaynakURL": "https://www.verikaynagi.com/grafik/yillara-gore-ortalama-tavuk-eti-fiyati-2009-2019/", "dogrulama": "dogrulanmis", "not": "TÜİK yıllık ortalama (1 kg)" },
  { "itemId": "tavuk", "yil": 2007, "deger": 4.34, "tip": "ortalama", "kaynakTipi": "elle", "kaynakAdi": "TÜİK", "kaynakURL": "https://www.verikaynagi.com/grafik/yillara-gore-ortalama-tavuk-eti-fiyati-2009-2019/", "dogrulama": "dogrulanmis", "not": "TÜİK yıllık ortalama (1 kg)" },
  { "itemId": "tavuk", "yil": 2008, "deger": 4.40, "tip": "ortalama", "kaynakTipi": "elle", "kaynakAdi": "TÜİK", "kaynakURL": "https://www.verikaynagi.com/grafik/yillara-gore-ortalama-tavuk-eti-fiyati-2009-2019/", "dogrulama": "dogrulanmis", "not": "TÜİK yıllık ortalama (1 kg)" },
  { "itemId": "tavuk", "yil": 2009, "deger": 5.48, "tip": "ortalama", "kaynakTipi": "elle", "kaynakAdi": "TÜİK", "kaynakURL": "https://www.verikaynagi.com/grafik/yillara-gore-ortalama-tavuk-eti-fiyati-2009-2019/", "dogrulama": "dogrulanmis", "not": "TÜİK yıllık ortalama (1 kg)" },
  { "itemId": "tavuk", "yil": 2010, "deger": 5.79, "tip": "ortalama", "kaynakTipi": "elle", "kaynakAdi": "TÜİK", "kaynakURL": "https://www.verikaynagi.com/grafik/yillara-gore-ortalama-tavuk-eti-fiyati-2009-2019/", "dogrulama": "dogrulanmis", "not": "TÜİK yıllık ortalama (1 kg)" },
  { "itemId": "tavuk", "yil": 2011, "deger": 5.84, "tip": "ortalama", "kaynakTipi": "elle", "kaynakAdi": "TÜİK", "kaynakURL": "https://www.verikaynagi.com/grafik/yillara-gore-ortalama-tavuk-eti-fiyati-2009-2019/", "dogrulama": "dogrulanmis", "not": "TÜİK yıllık ortalama (1 kg)" },
  { "itemId": "tavuk", "yil": 2012, "deger": 6.62, "tip": "ortalama", "kaynakTipi": "elle", "kaynakAdi": "TÜİK", "kaynakURL": "https://www.verikaynagi.com/grafik/yillara-gore-ortalama-tavuk-eti-fiyati-2009-2019/", "dogrulama": "dogrulanmis", "not": "TÜİK yıllık ortalama (1 kg)" },
  { "itemId": "tavuk", "yil": 2013, "deger": 6.81, "tip": "ortalama", "kaynakTipi": "elle", "kaynakAdi": "TÜİK", "kaynakURL": "https://www.verikaynagi.com/grafik/yillara-gore-ortalama-tavuk-eti-fiyati-2009-2019/", "dogrulama": "dogrulanmis", "not": "TÜİK yıllık ortalama (1 kg)" },
  { "itemId": "tavuk", "yil": 2014, "deger": 7.27, "tip": "ortalama", "kaynakTipi": "elle", "kaynakAdi": "TÜİK", "kaynakURL": "https://www.verikaynagi.com/grafik/yillara-gore-ortalama-tavuk-eti-fiyati-2009-2019/", "dogrulama": "dogrulanmis", "not": "TÜİK yıllık ortalama (1 kg)" },
  { "itemId": "tavuk", "yil": 2015, "deger": 7.25, "tip": "ortalama", "kaynakTipi": "elle", "kaynakAdi": "TÜİK", "kaynakURL": "https://www.verikaynagi.com/grafik/yillara-gore-ortalama-tavuk-eti-fiyati-2009-2019/", "dogrulama": "dogrulanmis", "not": "TÜİK yıllık ortalama (1 kg)" },
  { "itemId": "tavuk", "yil": 2016, "deger": 7.86, "tip": "ortalama", "kaynakTipi": "elle", "kaynakAdi": "TÜİK", "kaynakURL": "https://www.verikaynagi.com/grafik/yillara-gore-ortalama-tavuk-eti-fiyati-2009-2019/", "dogrulama": "dogrulanmis", "not": "TÜİK yıllık ortalama (1 kg)" },
  { "itemId": "tavuk", "yil": 2017, "deger": 8.93, "tip": "ortalama", "kaynakTipi": "elle", "kaynakAdi": "TÜİK", "kaynakURL": "https://www.verikaynagi.com/grafik/yillara-gore-ortalama-tavuk-eti-fiyati-2009-2019/", "dogrulama": "dogrulanmis", "not": "TÜİK yıllık ortalama (1 kg)" },
  { "itemId": "tavuk", "yil": 2018, "deger": 9.85, "tip": "ortalama", "kaynakTipi": "elle", "kaynakAdi": "TÜİK", "kaynakURL": "https://www.verikaynagi.com/grafik/yillara-gore-ortalama-tavuk-eti-fiyati-2009-2019/", "dogrulama": "dogrulanmis", "not": "TÜİK yıllık ortalama (1 kg)" },
  { "itemId": "tavuk", "yil": 2019, "deger": 12.06, "tip": "ortalama", "kaynakTipi": "elle", "kaynakAdi": "TÜİK", "kaynakURL": "https://www.verikaynagi.com/grafik/yillara-gore-ortalama-tavuk-eti-fiyati-2009-2019/", "dogrulama": "dogrulanmis", "not": "TÜİK yıllık ortalama (1 kg)" },
  { "itemId": "tavuk", "yil": 2020, "deger": 12.47, "tip": "ortalama", "kaynakTipi": "elle", "kaynakAdi": "TÜİK", "kaynakURL": "https://www.verikaynagi.com/grafik/yillara-gore-ortalama-tavuk-eti-fiyati-2009-2019/", "dogrulama": "dogrulanmis", "not": "TÜİK yıllık ortalama (1 kg)" },
  { "itemId": "tavuk", "yil": 2021, "deger": 19.20, "tip": "ortalama", "kaynakTipi": "elle", "kaynakAdi": "TÜİK", "kaynakURL": "https://www.verikaynagi.com/grafik/yillara-gore-ortalama-tavuk-eti-fiyati-2009-2019/", "dogrulama": "dogrulanmis", "not": "TÜİK yıllık ortalama (1 kg); seri Nisan 2022'de bitiyor" },

  { "itemId": "yumurta", "yil": 2005, "deger": 0.13, "tip": "ortalama", "kaynakTipi": "elle", "kaynakAdi": "TÜİK", "kaynakURL": "https://www.verikaynagi.com/grafik/yillara-gore-ortalama-yumurta-fiyati-2009-2019/", "dogrulama": "dogrulanmis", "not": "TÜİK aylık yumurta (adet) fiyatlarından yıllık ortalama; verikaynagi (Playwright/XHR)" },
  { "itemId": "yumurta", "yil": 2006, "deger": 0.15, "tip": "ortalama", "kaynakTipi": "elle", "kaynakAdi": "TÜİK", "kaynakURL": "https://www.verikaynagi.com/grafik/yillara-gore-ortalama-yumurta-fiyati-2009-2019/", "dogrulama": "dogrulanmis", "not": "TÜİK yıllık ortalama (adet)" },
  { "itemId": "yumurta", "yil": 2007, "deger": 0.20, "tip": "ortalama", "kaynakTipi": "elle", "kaynakAdi": "TÜİK", "kaynakURL": "https://www.verikaynagi.com/grafik/yillara-gore-ortalama-yumurta-fiyati-2009-2019/", "dogrulama": "dogrulanmis", "not": "TÜİK yıllık ortalama (adet)" },
  { "itemId": "yumurta", "yil": 2008, "deger": 0.20, "tip": "ortalama", "kaynakTipi": "elle", "kaynakAdi": "TÜİK", "kaynakURL": "https://www.verikaynagi.com/grafik/yillara-gore-ortalama-yumurta-fiyati-2009-2019/", "dogrulama": "dogrulanmis", "not": "TÜİK yıllık ortalama (adet)" },
  { "itemId": "yumurta", "yil": 2009, "deger": 0.23, "tip": "ortalama", "kaynakTipi": "elle", "kaynakAdi": "TÜİK", "kaynakURL": "https://www.verikaynagi.com/grafik/yillara-gore-ortalama-yumurta-fiyati-2009-2019/", "dogrulama": "dogrulanmis", "not": "TÜİK yıllık ortalama (adet)" },
  { "itemId": "yumurta", "yil": 2010, "deger": 0.21, "tip": "ortalama", "kaynakTipi": "elle", "kaynakAdi": "TÜİK", "kaynakURL": "https://www.verikaynagi.com/grafik/yillara-gore-ortalama-yumurta-fiyati-2009-2019/", "dogrulama": "dogrulanmis", "not": "TÜİK yıllık ortalama (adet)" },
  { "itemId": "yumurta", "yil": 2011, "deger": 0.25, "tip": "ortalama", "kaynakTipi": "elle", "kaynakAdi": "TÜİK", "kaynakURL": "https://www.verikaynagi.com/grafik/yillara-gore-ortalama-yumurta-fiyati-2009-2019/", "dogrulama": "dogrulanmis", "not": "TÜİK yıllık ortalama (adet)" },
  { "itemId": "yumurta", "yil": 2012, "deger": 0.29, "tip": "ortalama", "kaynakTipi": "elle", "kaynakAdi": "TÜİK", "kaynakURL": "https://www.verikaynagi.com/grafik/yillara-gore-ortalama-yumurta-fiyati-2009-2019/", "dogrulama": "dogrulanmis", "not": "TÜİK yıllık ortalama (adet)" },
  { "itemId": "yumurta", "yil": 2013, "deger": 0.30, "tip": "ortalama", "kaynakTipi": "elle", "kaynakAdi": "TÜİK", "kaynakURL": "https://www.verikaynagi.com/grafik/yillara-gore-ortalama-yumurta-fiyati-2009-2019/", "dogrulama": "dogrulanmis", "not": "TÜİK yıllık ortalama (adet)" },
  { "itemId": "yumurta", "yil": 2014, "deger": 0.36, "tip": "ortalama", "kaynakTipi": "elle", "kaynakAdi": "TÜİK", "kaynakURL": "https://www.verikaynagi.com/grafik/yillara-gore-ortalama-yumurta-fiyati-2009-2019/", "dogrulama": "dogrulanmis", "not": "TÜİK yıllık ortalama (adet)" },
  { "itemId": "yumurta", "yil": 2015, "deger": 0.39, "tip": "ortalama", "kaynakTipi": "elle", "kaynakAdi": "TÜİK", "kaynakURL": "https://www.verikaynagi.com/grafik/yillara-gore-ortalama-yumurta-fiyati-2009-2019/", "dogrulama": "dogrulanmis", "not": "TÜİK yıllık ortalama (adet)" },
  { "itemId": "yumurta", "yil": 2016, "deger": 0.38, "tip": "ortalama", "kaynakTipi": "elle", "kaynakAdi": "TÜİK", "kaynakURL": "https://www.verikaynagi.com/grafik/yillara-gore-ortalama-yumurta-fiyati-2009-2019/", "dogrulama": "dogrulanmis", "not": "TÜİK yıllık ortalama (adet)" },
  { "itemId": "yumurta", "yil": 2017, "deger": 0.45, "tip": "ortalama", "kaynakTipi": "elle", "kaynakAdi": "TÜİK", "kaynakURL": "https://www.verikaynagi.com/grafik/yillara-gore-ortalama-yumurta-fiyati-2009-2019/", "dogrulama": "dogrulanmis", "not": "TÜİK yıllık ortalama (adet)" },
  { "itemId": "yumurta", "yil": 2018, "deger": 0.56, "tip": "ortalama", "kaynakTipi": "elle", "kaynakAdi": "TÜİK", "kaynakURL": "https://www.verikaynagi.com/grafik/yillara-gore-ortalama-yumurta-fiyati-2009-2019/", "dogrulama": "dogrulanmis", "not": "TÜİK yıllık ortalama (adet)" },
  { "itemId": "yumurta", "yil": 2019, "deger": 0.50, "tip": "ortalama", "kaynakTipi": "elle", "kaynakAdi": "TÜİK", "kaynakURL": "https://www.verikaynagi.com/grafik/yillara-gore-ortalama-yumurta-fiyati-2009-2019/", "dogrulama": "dogrulanmis", "not": "TÜİK yıllık ortalama (adet)" },
  { "itemId": "yumurta", "yil": 2020, "deger": 0.63, "tip": "ortalama", "kaynakTipi": "elle", "kaynakAdi": "TÜİK", "kaynakURL": "https://www.verikaynagi.com/grafik/yillara-gore-ortalama-yumurta-fiyati-2009-2019/", "dogrulama": "dogrulanmis", "not": "TÜİK yıllık ortalama (adet)" },
  { "itemId": "yumurta", "yil": 2021, "deger": 0.92, "tip": "ortalama", "kaynakTipi": "elle", "kaynakAdi": "TÜİK", "kaynakURL": "https://www.verikaynagi.com/grafik/yillara-gore-ortalama-yumurta-fiyati-2009-2019/", "dogrulama": "dogrulanmis", "not": "TÜİK yıllık ortalama (adet); seri Ocak 2022'de bitiyor" },

  { "itemId": "patates", "yil": 2005, "deger": 0.56, "tip": "ortalama", "kaynakTipi": "elle", "kaynakAdi": "TÜİK", "kaynakURL": "https://www.verikaynagi.com/grafik/yillara-gore-ortalama-patates-fiyati-2009-2020/", "dogrulama": "dogrulanmis", "not": "TÜİK aylık patates (1 kg) fiyatlarından yıllık ortalama; verikaynagi (Playwright/XHR)" },
  { "itemId": "patates", "yil": 2006, "deger": 0.73, "tip": "ortalama", "kaynakTipi": "elle", "kaynakAdi": "TÜİK", "kaynakURL": "https://www.verikaynagi.com/grafik/yillara-gore-ortalama-patates-fiyati-2009-2020/", "dogrulama": "dogrulanmis", "not": "TÜİK yıllık ortalama (1 kg)" },
  { "itemId": "patates", "yil": 2007, "deger": 0.75, "tip": "ortalama", "kaynakTipi": "elle", "kaynakAdi": "TÜİK", "kaynakURL": "https://www.verikaynagi.com/grafik/yillara-gore-ortalama-patates-fiyati-2009-2020/", "dogrulama": "dogrulanmis", "not": "TÜİK yıllık ortalama (1 kg)" },
  { "itemId": "patates", "yil": 2008, "deger": 0.81, "tip": "ortalama", "kaynakTipi": "elle", "kaynakAdi": "TÜİK", "kaynakURL": "https://www.verikaynagi.com/grafik/yillara-gore-ortalama-patates-fiyati-2009-2020/", "dogrulama": "dogrulanmis", "not": "TÜİK yıllık ortalama (1 kg)" },
  { "itemId": "patates", "yil": 2009, "deger": 0.99, "tip": "ortalama", "kaynakTipi": "elle", "kaynakAdi": "TÜİK", "kaynakURL": "https://www.verikaynagi.com/grafik/yillara-gore-ortalama-patates-fiyati-2009-2020/", "dogrulama": "dogrulanmis", "not": "TÜİK yıllık ortalama (1 kg)" },
  { "itemId": "patates", "yil": 2010, "deger": 1.07, "tip": "ortalama", "kaynakTipi": "elle", "kaynakAdi": "TÜİK", "kaynakURL": "https://www.verikaynagi.com/grafik/yillara-gore-ortalama-patates-fiyati-2009-2020/", "dogrulama": "dogrulanmis", "not": "TÜİK yıllık ortalama (1 kg)" },
  { "itemId": "patates", "yil": 2011, "deger": 1.25, "tip": "ortalama", "kaynakTipi": "elle", "kaynakAdi": "TÜİK", "kaynakURL": "https://www.verikaynagi.com/grafik/yillara-gore-ortalama-patates-fiyati-2009-2020/", "dogrulama": "dogrulanmis", "not": "TÜİK yıllık ortalama (1 kg)" },
  { "itemId": "patates", "yil": 2012, "deger": 0.96, "tip": "ortalama", "kaynakTipi": "elle", "kaynakAdi": "TÜİK", "kaynakURL": "https://www.verikaynagi.com/grafik/yillara-gore-ortalama-patates-fiyati-2009-2020/", "dogrulama": "dogrulanmis", "not": "TÜİK yıllık ortalama (1 kg)" },
  { "itemId": "patates", "yil": 2013, "deger": 1.32, "tip": "ortalama", "kaynakTipi": "elle", "kaynakAdi": "TÜİK", "kaynakURL": "https://www.verikaynagi.com/grafik/yillara-gore-ortalama-patates-fiyati-2009-2020/", "dogrulama": "dogrulanmis", "not": "TÜİK yıllık ortalama (1 kg)" },
  { "itemId": "patates", "yil": 2014, "deger": 2.15, "tip": "ortalama", "kaynakTipi": "elle", "kaynakAdi": "TÜİK", "kaynakURL": "https://www.verikaynagi.com/grafik/yillara-gore-ortalama-patates-fiyati-2009-2020/", "dogrulama": "dogrulanmis", "not": "TÜİK yıllık ortalama (1 kg)" },
  { "itemId": "patates", "yil": 2015, "deger": 2.05, "tip": "ortalama", "kaynakTipi": "elle", "kaynakAdi": "TÜİK", "kaynakURL": "https://www.verikaynagi.com/grafik/yillara-gore-ortalama-patates-fiyati-2009-2020/", "dogrulama": "dogrulanmis", "not": "TÜİK yıllık ortalama (1 kg)" },
  { "itemId": "patates", "yil": 2016, "deger": 1.22, "tip": "ortalama", "kaynakTipi": "elle", "kaynakAdi": "TÜİK", "kaynakURL": "https://www.verikaynagi.com/grafik/yillara-gore-ortalama-patates-fiyati-2009-2020/", "dogrulama": "dogrulanmis", "not": "TÜİK yıllık ortalama (1 kg)" },
  { "itemId": "patates", "yil": 2017, "deger": 1.61, "tip": "ortalama", "kaynakTipi": "elle", "kaynakAdi": "TÜİK", "kaynakURL": "https://www.verikaynagi.com/grafik/yillara-gore-ortalama-patates-fiyati-2009-2020/", "dogrulama": "dogrulanmis", "not": "TÜİK yıllık ortalama (1 kg)" },
  { "itemId": "patates", "yil": 2018, "deger": 2.40, "tip": "ortalama", "kaynakTipi": "elle", "kaynakAdi": "TÜİK", "kaynakURL": "https://www.verikaynagi.com/grafik/yillara-gore-ortalama-patates-fiyati-2009-2020/", "dogrulama": "dogrulanmis", "not": "TÜİK yıllık ortalama (1 kg)" },
  { "itemId": "patates", "yil": 2019, "deger": 3.12, "tip": "ortalama", "kaynakTipi": "elle", "kaynakAdi": "TÜİK", "kaynakURL": "https://www.verikaynagi.com/grafik/yillara-gore-ortalama-patates-fiyati-2009-2020/", "dogrulama": "dogrulanmis", "not": "TÜİK yıllık ortalama (1 kg)" },
  { "itemId": "patates", "yil": 2020, "deger": 2.56, "tip": "ortalama", "kaynakTipi": "elle", "kaynakAdi": "TÜİK", "kaynakURL": "https://www.verikaynagi.com/grafik/yillara-gore-ortalama-patates-fiyati-2009-2020/", "dogrulama": "dogrulanmis", "not": "TÜİK yıllık ortalama (1 kg)" },
  { "itemId": "patates", "yil": 2021, "deger": 2.89, "tip": "ortalama", "kaynakTipi": "elle", "kaynakAdi": "TÜİK", "kaynakURL": "https://www.verikaynagi.com/grafik/yillara-gore-ortalama-patates-fiyati-2009-2020/", "dogrulama": "dogrulanmis", "not": "TÜİK yıllık ortalama (1 kg); seri ~2022'de bitiyor" }
]
